secrets_mgmt_cli/__init__.py
secrets_mgmt_cli/__main__.py
secrets_mgmt_cli/aws.py
secrets_mgmt_cli/cli.py
secrets_mgmt_cli/config.py
secrets_mgmt_cli/utils.py
secrets_mgmt_cli-0.5.0.dist-info/LICENSE
secrets_mgmt_cli-0.5.0.dist-info/METADATA
secrets_mgmt_cli-0.5.0.dist-info/WHEEL
secrets_mgmt_cli-0.5.0.dist-info/entry_points.txt
secrets_mgmt_cli-0.5.0.dist-info/top_level.txt
secrets_mgmt_cli-0.5.0.dist-info/RECORD
