Metadata-Version: 2.1
Name: secrets-mgmt-cli
Version: 0.5.0
Summary: A simple CLI for managing secrets in AWS Secrets Manager
Home-page: https://github.com/william-cass-wright/secrets-mgmt-cli
Author: Will Wright
License: Apache License, Version 2.0
Project-URL: Issues, https://github.com/william-cass-wright/secrets-mgmt-cli/issues
Project-URL: CI, https://github.com/william-cass-wright/secrets-mgmt-cli/actions
Project-URL: Changelog, https://github.com/william-cass-wright/secrets-mgmt-cli/releases
Requires-Python: >=3.7
License-File: LICENSE
Requires-Dist: click
Requires-Dist: boto3
Provides-Extra: test
Requires-Dist: pytest ; extra == 'test'
